[
  {
    "id": "1",
    "striptitle": "Listing Requisites",
    "stripdesc": "Clear documentation of requirements, features, and functionality to align expectations and avoid confusion.",
    "stripicon": "/listing_the_requisits.png"
  },
  {
    "id": "2",
    "striptitle": "Absolute Web Development",
    "stripdesc": "Building your website using the latest technologies, ensuring robust and scalable performance.",
    "stripicon": "/absolute_web_development.png"
  },
  {
    "id": "3",
    "striptitle": "Ultimate Web Launch",
    "stripdesc": "Seamlessly deploying your website with a smooth transition from development to live status.",
    "stripicon": "/ultimate_web_launch.png"
  },
  {
    "id": "4",
    "striptitle": "Project Closure and Review",
    "stripdesc": "Once the project is completed, we conduct a thorough review to ensure all deliverables meet the defined standards and objectives. We gather lessons learned to refine future projects and provide final documentation to clients.",
    "stripicon": "/project_closure_and_review.png"
  }
]
